basicrpg/__init__.py
basicrpg/basics.py
basicrpg/components.py
basicrpg/errors.py
basicrpg/generators.py
basicrpg/items.py
bascirpg-0.0.2.dist-info/LICENSE
bascirpg-0.0.2.dist-info/METADATA
bascirpg-0.0.2.dist-info/WHEEL
bascirpg-0.0.2.dist-info/top_level.txt
bascirpg-0.0.2.dist-info/RECORD
