Metadata-Version: 2.1
Name: bascirpg
Version: 0.0.2
Summary: Python library for making RPG games, clean and easy.
Home-page: https://github.com/Unlisted27/basicrpg
Author: Unlisted_dev
Classifier: Programming Language :: Python :: 3
Classifier: License :: OSI Approved :: MIT License
Classifier: Operating System :: OS Independent
Requires-Python: >=3.6
License-File: LICENSE
